YARW/__init__.py
YARW/_version.py
YARW-0.1.5.dist-info/DESCRIPTION.rst
YARW-0.1.5.dist-info/METADATA
YARW-0.1.5.dist-info/RECORD
YARW-0.1.5.dist-info/WHEEL
YARW-0.1.5.dist-info/metadata.json
YARW-0.1.5.dist-info/top_level.txt
