Metadata-Version: 2.0
Name: YARW
Version: 0.1.5
Summary: Yet Another Registry Wrapper
Home-page: https://github.com/xoviat/subzero
Author: Mars Galactic
Author-email: xoviat@users.noreply.github.com
License: GNU GENERAL PUBLIC LICENSE
Platform: any
